VelocityConversion/AlphaDB.csv
VelocityConversion/MantleConversion.py
VelocityConversion/MinDB.csv
VelocityConversion/__init__.py
VelocityConversion/__main__.py
VelocityConversion/_version.py
velocityconversion-1.1.2.dist-info/LICENSE
velocityconversion-1.1.2.dist-info/METADATA
velocityconversion-1.1.2.dist-info/WHEEL
velocityconversion-1.1.2.dist-info/top_level.txt
velocityconversion-1.1.2.dist-info/RECORD
