Metadata-Version: 2.1
Name: velocityconversion
Version: 1.1.2
Summary: Conversion of seismic velocities to temperature and density
Home-page: https://github.com/cmeessen/VelocityConversion
Author: Christian Meeßen
Author-email: christian.meessen@gfz-potsdam.de
License: UNKNOWN
Platform: UNKNOWN
Classifier: Natural Language :: English
Classifier: Programming Language :: Python :: 3
Classifier: Programming Language :: Python :: 3.7
Classifier: Programming Language :: Python :: 3.8
Classifier: Programming Language :: Python :: 3.9
Classifier: License :: OSI Approved :: GNU General Public License v3 (GPLv3)
Classifier: Operating System :: OS Independent
Classifier: Topic :: Scientific/Engineering :: Physics
License-File: LICENSE
Requires-Dist: numpy
